{
	"name": "04-DL-Load-Raw-to-Delta-Table",
	"properties": {
		"activities": [
			{
				"name": "Set-ClusterType",
				"type": "SetVariable",
				"dependsOn": [],
				"userProperties": [],
				"typeProperties": {
					"variableName": "ClusterType",
					"value": {
						"value": "@toLower(last(split(pipeline().parameters.TaskDetails.Processor,'|')))",
						"type": "Expression"
					}
				}
			},
			{
				"name": "If-ClusterType",
				"type": "IfCondition",
				"dependsOn": [
					{
						"activity": "Set-ClusterType",
						"dependencyConditions": [
							"Succeeded"
						]
					}
				],
				"userProperties": [],
				"typeProperties": {
					"expression": {
						"value": "@equals(variables('ClusterType'), 'interactive')",
						"type": "Expression"
					},
					"ifFalseActivities": [
						{
							"name": "Notebook-Delta-Table-Job",
							"type": "DatabricksNotebook",
							"dependsOn": [],
							"policy": {
								"timeout": "7.00:00:00",
								"retry": 0,
								"retryIntervalInSeconds": 30,
								"secureOutput": false,
								"secureInput": false
							},
							"userProperties": [],
							"typeProperties": {
								"notebookPath": {
									"value": "@variables('NoteBookURL')",
									"type": "Expression"
								},
								"baseParameters": {
									"file_object": {
										"value": "@concat(pipeline().parameters.TargetBLOBFolder,pipeline().parameters.TargetBLOBName)",
										"type": "Expression"
									},
									"source_param": {
										"value": "@string(pipeline().parameters.TaskDetails)",
										"type": "Expression"
									},
									"file_date_time_stamp": {
										"value": "@pipeline().parameters.SourceFileDateTimeStamp",
										"type": "Expression"
									}
								}
							},
							"linkedServiceName": {
								"referenceName": "LS-AzureDatabricks_JobCluster",
								"type": "LinkedServiceReference",
								"parameters": {
									"kvSecret": {
										"value": "@split(pipeline().parameters.TaskDetails.Processor,'|')[0]",
										"type": "Expression"
									},
									"DataBricksClusterType": {
										"value": "@split(pipeline().parameters.TaskDetails.Processor,'|')[2]",
										"type": "Expression"
									},
									"DataBricksClusterVersion": {
										"value": "@split(pipeline().parameters.TaskDetails.Processor,'|')[3]",
										"type": "Expression"
									},
									"DataBricksWorkerNodes": {
										"value": "@split(pipeline().parameters.TaskDetails.Processor,'|')[4]",
										"type": "Expression"
									}
								}
							}
						},
						{
							"name": "Set-ReturnValue-Job",
							"type": "SetVariable",
							"dependsOn": [
								{
									"activity": "Notebook-Delta-Table-Job",
									"dependencyConditions": [
										"Succeeded"
									]
								}
							],
							"userProperties": [],
							"typeProperties": {
								"variableName": "ReturnValue",
								"value": {
									"value": "@string(activity('Notebook-Delta-Table-Job').output.runOutput)",
									"type": "Expression"
								}
							}
						}
					],
					"ifTrueActivities": [
						{
							"name": "Notebook-Delta-Table-Interactive",
							"type": "DatabricksNotebook",
							"dependsOn": [],
							"policy": {
								"timeout": "7.00:00:00",
								"retry": 0,
								"retryIntervalInSeconds": 30,
								"secureOutput": false,
								"secureInput": false
							},
							"userProperties": [],
							"typeProperties": {
								"notebookPath": {
									"value": "@variables('NoteBookURL')",
									"type": "Expression"
								},
								"baseParameters": {
									"file_object": {
										"value": "@concat(pipeline().parameters.TargetBLOBFolder,pipeline().parameters.TargetBLOBName)",
										"type": "Expression"
									},
									"source_param": {
										"value": "@string(pipeline().parameters.TaskDetails)",
										"type": "Expression"
									},
									"file_date_time_stamp": {
										"value": "@pipeline().parameters.SourceFileDateTimeStamp",
										"type": "Expression"
									}
								}
							},
							"linkedServiceName": {
								"referenceName": "LS-AzureDatabricks_DefinedCluster",
								"type": "LinkedServiceReference",
								"parameters": {
									"kvSecret": {
										"value": "@split(pipeline().parameters.TaskDetails.Processor,'|')[0]",
										"type": "Expression"
									},
									"clusterId": {
										"value": "@split(pipeline().parameters.TaskDetails.Processor,'|')[1]",
										"type": "Expression"
									}
								}
							}
						},
						{
							"name": "Set-ReturnValue-Interactive",
							"type": "SetVariable",
							"dependsOn": [
								{
									"activity": "Notebook-Delta-Table-Interactive",
									"dependencyConditions": [
										"Succeeded"
									]
								}
							],
							"userProperties": [],
							"typeProperties": {
								"variableName": "ReturnValue",
								"value": {
									"value": "@string(activity('Notebook-Delta-Table-Interactive').output.runOutput)",
									"type": "Expression"
								}
							}
						}
					]
				}
			},
			{
				"name": "SP-Update-Manifest-Delta-Records",
				"type": "SqlServerStoredProcedure",
				"dependsOn": [
					{
						"activity": "If-ClusterType",
						"dependencyConditions": [
							"Succeeded"
						]
					}
				],
				"policy": {
					"timeout": "7.00:00:00",
					"retry": 0,
					"retryIntervalInSeconds": 30,
					"secureOutput": false,
					"secureInput": false
				},
				"userProperties": [],
				"typeProperties": {
					"storedProcedureName": "[CTL].[UpdateManifestDeltaRecords]",
					"storedProcedureParameters": {
						"BatchExecutionLogID": {
							"value": {
								"value": "@pipeline().parameters.BatchLogId",
								"type": "Expression"
							},
							"type": "Int64"
						},
						"TaskExecutionLogID": {
							"value": {
								"value": "@pipeline().parameters.TaskExecutionLogId",
								"type": "Expression"
							},
							"type": "Int64"
						},
						"RecordsDeltaTable": {
							"value": {
								"value": "@variables('ReturnValue')",
								"type": "Expression"
							},
							"type": "Int64"
						},
						"SourceFileDateStamp": {
							"value": {
								"value": "@pipeline().parameters.SourceFileDateTimeStamp",
								"type": "Expression"
							},
							"type": "String"
						}
					}
				},
				"linkedServiceName": {
					"referenceName": "LS-AzureSqlDatabase_Ctrldb",
					"type": "LinkedServiceReference",
					"parameters": {
						"kvSecret": "daf-sql-controldb-connectionstring"
					}
				}
			}
		],
		"parameters": {
			"BatchLogID": {
				"type": "int",
				"defaultValue": 1
			},
			"TaskExecutionLogId": {
				"type": "int",
				"defaultValue": 1
			},
			"TaskDetails": {
				"type": "object"
			},
			"TargetBLOBFolder": {
				"type": "string",
				"defaultValue": "raw"
			},
			"TargetBLOBName": {
				"type": "string",
				"defaultValue": "targetdirectory"
			},
			"ProjectRunID": {
				"type": "string"
			},
			"SourceFileName": {
				"type": "string"
			},
			"SourceFileDateTimeStamp": {
				"type": "string"
			}
		},
		"variables": {
			"ReturnValue": {
				"type": "String"
			},
			"ClusterType": {
				"type": "String"
			},
			"NoteBookURL": {
				"type": "String",
				"defaultValue": "/Repos/o3an@sydneywater.com.au/DAFPOCREPO1/Databricks/notebooks/raw/load-raw-deltatable"
			}
		},
		"folder": {
			"name": "Data Lake"
		},
		"annotations": [],
		"lastPublishTime": "2021-06-30T03:14:35Z"
	},
	"type": "Microsoft.DataFactory/factories/pipelines"
}