{
	"name": "BINARY_FILESERVER",
	"properties": {
		"linkedServiceName": {
			"referenceName": "LS_FileServer",
			"type": "LinkedServiceReference",
			"parameters": {
				"UserID": {
					"value": "@dataset().FileShareUserID",
					"type": "Expression"
				},
				"URL": {
					"value": "@dataset().FileShareURL",
					"type": "Expression"
				},
				"Password": {
					"value": "@dataset().FileSharePassword",
					"type": "Expression"
				}
			}
		},
		"parameters": {
			"FileShareUserID": {
				"type": "string",
				"defaultValue": "srvEDWSMFT@tafenswtest.edu.au"
			},
			"Folder": {
				"type": "string"
			},
			"File": {
				"type": "string"
			},
			"FileShareURL": {
				"type": "string",
				"defaultValue": "FileServer-URL"
			},
			"FileSharePassword": {
				"type": "string",
				"defaultValue": "FileServer-ServiceAccount-Password"
			}
		},
		"annotations": [],
		"type": "Binary",
		"typeProperties": {
			"location": {
				"type": "FileServerLocation",
				"fileName": {
					"value": "@dataset().File",
					"type": "Expression"
				},
				"folderPath": {
					"value": "@dataset().Folder",
					"type": "Expression"
				}
			}
		}
	}
}