{
	"name": "LS-AzureDatabricks_DefinedCluster",
	"properties": {
		"parameters": {
			"kvSecret": {
				"type": "string",
				"defaultValue": "databricks-token"
			},
			"clusterId": {
				"type": "string",
				"defaultValue": "0705-044124-gored835"
			}
		},
		"annotations": [],
		"type": "AzureDatabricks",
		"typeProperties": {
			"domain": "https://adb-6510910994889.9.azuredatabricks.net/",
			"accessToken": {
				"type": "AzureKeyVaultSecret",
				"store": {
					"referenceName": "LS-AzureKeyVault",
					"type": "LinkedServiceReference"
				},
				"secretName": {
					"value": "@linkedService().kvSecret",
					"type": "Expression"
				},
				"secretVersion": ""
			},
			"existingClusterId": "@linkedService().clusterId"
		},
		"connectVia": {
			"referenceName": "IntegrationRuntime-SelfHosted",
			"type": "IntegrationRuntimeReference"
		}
	},
	"type": "Microsoft.DataFactory/factories/linkedservices"
}